jackass/__init__.py
jackass-1.9.69.dist-info/METADATA
jackass-1.9.69.dist-info/WHEEL
jackass-1.9.69.dist-info/RECORD
