Metadata-Version: 2.1
Name: jackass
Version: 1.9.69
Summary: best shit i ever listened to ngl
Author: Predeactor
Author-email: pro.julien.mauroy@gmail.com
Requires-Python: >=3,<4
Classifier: Programming Language :: Python :: 3
Classifier: Programming Language :: Python :: 3.4
Classifier: Programming Language :: Python :: 3.5
Classifier: Programming Language :: Python :: 3.6
Classifier: Programming Language :: Python :: 3.7
Classifier: Programming Language :: Python :: 3.8
Classifier: Programming Language :: Python :: 3.9
Classifier: Programming Language :: Python :: 3.10
Classifier: Programming Language :: Python :: 3.11
